README.rst
setup.cfg
setup.py
clintrials/__init__.py
clintrials/coll.py
clintrials/common.py
clintrials/recruitment.py
clintrials/simulation.py
clintrials/stats.py
clintrials/tte.py
clintrials/util.py
clintrials.egg-info/PKG-INFO
clintrials.egg-info/SOURCES.txt
clintrials.egg-info/dependency_links.txt
clintrials.egg-info/top_level.txt
clintrials/dosefinding/__init__.py
clintrials/dosefinding/crm.py
clintrials/dosefinding/efficacytoxicity.py
clintrials/dosefinding/efftox.py
clintrials/dosefinding/wagestait.py
clintrials/dosefinding/watu.py
clintrials/phase2/__init__.py
clintrials/phase2/simple.py
clintrials/phase2/bebop/__init__.py
clintrials/phase2/bebop/peps2v1.py
clintrials/phase2/bebop/peps2v2.py