Metadata-Version: 1.1
Name: clintrials
Version: 0.1.4
Summary: clintrials is a library of clinical trial designs and methods in Python
Home-page: https://github.com/brockk/clintrials
Author: Kristian Brock
Author-email: kristian.brock@gmail.com
License: UNKNOWN
Download-URL: https://github.com/brockk/clintrials/tarball/0.1.4
Keywords: clinical,trial,biostatistics,medical,statistics
Platform: UNKNOWN
Classifier: Development Status :: 3 - Alpha
Classifier: Intended Audience :: Science/Research
Classifier: Topic :: Scientific/Engineering :: Medical Science Apps.
Classifier: License :: OSI Approved :: GNU General Public License v3 (GPLv3)
Classifier: Programming Language :: Python :: 2.7
Classifier: Programming Language :: Python :: 3.5
